torchgo42/__init__.py
torchgo42/torchgo42.py
torchgo42-0.1.1.dist-info/METADATA
torchgo42-0.1.1.dist-info/WHEEL
torchgo42-0.1.1.dist-info/top_level.txt
torchgo42-0.1.1.dist-info/RECORD
