Metadata-Version: 2.1
Name: torchgo42
Version: 0.1.1
Summary: zxczxczxc
Author: asd dasd
Requires-Python: >=3.6
Requires-Dist: pyperclip
Requires-Dist: mistralai
